abcd_seth/__init__.py
abcd_seth/dto/__init__.py
abcd_seth/models/__init__.py
abcd_seth/models/django/__init__.py
abcd_seth/models/django/user_model.py
abcd_seth/models/domain/__init__.py
abcd_seth/models/domain/user_model.py
abcd_seth-1.0.2.dist-info/METADATA
abcd_seth-1.0.2.dist-info/WHEEL
abcd_seth-1.0.2.dist-info/top_level.txt
abcd_seth-1.0.2.dist-info/RECORD
